{
  "$schema": "https://developer.microsoft.com/json-schemas/spfx-build/package-solution.schema.json",
  "solution": {
    "name": "hello-world-client-side-solution",
    "id": "7994e6af-db90-417c-b449-7fa496c1ea7d",
    "version": "1.0.0.0",
    "includeClientSideAssets": true,
    "skipFeatureDeployment": true,
    "isDomainIsolated": false,
    "developer": {
      "name": "",
      "websiteUrl": "",
      "privacyUrl": "",
      "termsOfUseUrl": "",
      "mpnId": "Undefined-1.19.0"
    },
    "metadata": {
      "shortDescription": {
        "default": "HelloWorld description"
      },
      "longDescription": {
        "default": "HelloWorld description"
      },
      "screenshotPaths": [],
      "videoUrl": "",
      "categories": []
    },
    "features": [
      {
        "title": "hello-world Feature",
        "description": "The feature that activates elements of the hello-world solution.",
        "id": "ae7d823b-c63d-45c5-8482-577c27b38769",
        "version": "1.0.0.0"
      }
    ]
  },
  "paths": {
    "zippedPackage": "solution/hello-world.sppkg"
  }
}
